crispy_forms_bootstrap2/__init__.py
crispy_forms_bootstrap2/templates/bootstrap/accordion-group.html
crispy_forms_bootstrap2/templates/bootstrap/accordion.html
crispy_forms_bootstrap2/templates/bootstrap/betterform.html
crispy_forms_bootstrap2/templates/bootstrap/display_form.html
crispy_forms_bootstrap2/templates/bootstrap/errors.html
crispy_forms_bootstrap2/templates/bootstrap/errors_formset.html
crispy_forms_bootstrap2/templates/bootstrap/field.html
crispy_forms_bootstrap2/templates/bootstrap/table_inline_formset.html
crispy_forms_bootstrap2/templates/bootstrap/uni_form.html
crispy_forms_bootstrap2/templates/bootstrap/uni_formset.html
crispy_forms_bootstrap2/templates/bootstrap/whole_uni_form.html
crispy_forms_bootstrap2/templates/bootstrap/whole_uni_formset.html
crispy_forms_bootstrap2/templates/bootstrap/layout/alert.html
crispy_forms_bootstrap2/templates/bootstrap/layout/baseinput.html
crispy_forms_bootstrap2/templates/bootstrap/layout/button.html
crispy_forms_bootstrap2/templates/bootstrap/layout/buttonholder.html
crispy_forms_bootstrap2/templates/bootstrap/layout/checkboxselectmultiple.html
crispy_forms_bootstrap2/templates/bootstrap/layout/checkboxselectmultiple_inline.html
crispy_forms_bootstrap2/templates/bootstrap/layout/column.html
crispy_forms_bootstrap2/templates/bootstrap/layout/div.html
crispy_forms_bootstrap2/templates/bootstrap/layout/field_errors.html
crispy_forms_bootstrap2/templates/bootstrap/layout/field_errors_block.html
crispy_forms_bootstrap2/templates/bootstrap/layout/field_with_buttons.html
crispy_forms_bootstrap2/templates/bootstrap/layout/fieldset.html
crispy_forms_bootstrap2/templates/bootstrap/layout/formactions.html
crispy_forms_bootstrap2/templates/bootstrap/layout/help_text.html
crispy_forms_bootstrap2/templates/bootstrap/layout/help_text_and_errors.html
crispy_forms_bootstrap2/templates/bootstrap/layout/multifield.html
crispy_forms_bootstrap2/templates/bootstrap/layout/prepended_appended_text.html
crispy_forms_bootstrap2-2024.1.dist-info/LICENSE
crispy_forms_bootstrap2-2024.1.dist-info/METADATA
crispy_forms_bootstrap2-2024.1.dist-info/WHEEL
crispy_forms_bootstrap2-2024.1.dist-info/top_level.txt
crispy_forms_bootstrap2-2024.1.dist-info/RECORD
